disk_block_check/__init__.py
disk_block_check/__main__.py
disk_block_check/__version__.py
disk_block_check/args.py
disk_block_check/error_handler.py
disk_block_check/logic.py
disk_block_check/low.py
disk_block_check/main.py
disk_block_check-0.7.0.dist-info/LICENSE
disk_block_check-0.7.0.dist-info/METADATA
disk_block_check-0.7.0.dist-info/WHEEL
disk_block_check-0.7.0.dist-info/entry_points.txt
disk_block_check-0.7.0.dist-info/top_level.txt
disk_block_check-0.7.0.dist-info/RECORD
