Metadata-Version: 2.1
Name: disk_block_check
Version: 0.7.0
License-File: LICENSE
Requires-Dist: argparse
Requires-Dist: tqdm
